pylint_exit.py
pylint_exit-1.2.0.dist-info/LICENSE
pylint_exit-1.2.0.dist-info/METADATA
pylint_exit-1.2.0.dist-info/WHEEL
pylint_exit-1.2.0.dist-info/entry_points.txt
pylint_exit-1.2.0.dist-info/top_level.txt
pylint_exit-1.2.0.dist-info/RECORD
