Metadata-Version: 2.1
Name: pylint-exit
Version: 1.2.0
Summary: Exit code handler for pylint command line utility.
Home-page: https://github.com/jongracecox/pylint-exit
Author: Jon Grace-Cox
Author-email: jongracecox@gmail.com
License: UNKNOWN
Platform: UNKNOWN
Classifier: License :: OSI Approved :: MIT License
